mtrampic_aws_utils/__init__.py
mtrampic_aws_utils/login_helper.py
mtrampic_aws_utils/main.py
mtrampic_aws_utils-0.1.1.dist-info/entry_points.txt
mtrampic_aws_utils-0.1.1.dist-info/LICENSE
mtrampic_aws_utils-0.1.1.dist-info/WHEEL
mtrampic_aws_utils-0.1.1.dist-info/METADATA
mtrampic_aws_utils-0.1.1.dist-info/RECORD
