Metadata-Version: 2.1
Name: mtrampic-aws-utils
Version: 0.1.1
Summary: Mini CLI to help work with AWS in Cross-Account setup.
License: MIT
Author: Mladen Trampic
Author-email: mladen@trampic.info
Requires-Python: >=3.6.1,<4.0.0
Classifier: License :: OSI Approved :: MIT License
Classifier: Programming Language :: Python :: 3
Classifier: Programming Language :: Python :: 3.10
Classifier: Programming Language :: Python :: 3.7
Classifier: Programming Language :: Python :: 3.8
Classifier: Programming Language :: Python :: 3.9
Requires-Dist: boto3 (>=1.21.22,<2.0.0)
Requires-Dist: pydantic (>=1.5.1,<2.0.0)
Requires-Dist: requests (>=2.27.1,<3.0.0)
Requires-Dist: typer-cli (==0.0.12)
